cmnemoi_learn/__init__.py
cmnemoi_learn/_abstract_model.py
cmnemoi_learn/classification/__init__.py
cmnemoi_learn/classification/_abstract_classifier.py
cmnemoi_learn/classification/_knn_classifier.py
cmnemoi_learn/classification/_logistic_regression.py
cmnemoi_learn/metrics.py
cmnemoi_learn/regression/__init__.py
cmnemoi_learn/regression/_abstract_regressor.py
cmnemoi_learn/regression/_linear_regression.py
cmnemoi_learn-0.5.0.dist-info/LICENSE.md
cmnemoi_learn-0.5.0.dist-info/METADATA
cmnemoi_learn-0.5.0.dist-info/WHEEL
cmnemoi_learn-0.5.0.dist-info/RECORD
