Metadata-Version: 2.1
Name: cmnemoi-learn
Version: 0.5.0
Summary: Machine Learning from scratch by Charles-Meldhine Madi Mnemoi
Home-page: https://github.com/cmnemoi/cmnemoi-learn.git
License: MIT
Author: Charles-Meldhine Madi Mnemoi
Author-email: charlesmeldhine.madimnemoi@gmail.com
Requires-Python: >=3.11,<4.0
Classifier: License :: OSI Approved :: MIT License
Classifier: Programming Language :: Python :: 3
Classifier: Programming Language :: Python :: 3.11
Classifier: Programming Language :: Python :: 3.12
Requires-Dist: numpy (>=1.25.2,<2.0.0)
Project-URL: Repository, https://github.com/cmnemoi/cmnemoi-learn.git
